odoo/addons/partner_tz/README.rst
odoo/addons/partner_tz/__init__.py
odoo/addons/partner_tz/__manifest__.py
odoo/addons/partner_tz/i18n/partner_tz.pot
odoo/addons/partner_tz/readme/CONTRIBUTORS.rst
odoo/addons/partner_tz/readme/CREDITS.rst
odoo/addons/partner_tz/readme/DESCRIPTION.rst
odoo/addons/partner_tz/readme/ROADMAP.rst
odoo/addons/partner_tz/static/description/icon.png
odoo/addons/partner_tz/static/description/index.html
odoo/addons/partner_tz/tools/__init__.py
odoo/addons/partner_tz/tools/tz_utils.py
odoo/addons/partner_tz/views/res_partner.xml
odoo14_addon_partner_tz-14.0.1.0.1.dist-info/METADATA
odoo14_addon_partner_tz-14.0.1.0.1.dist-info/WHEEL
odoo14_addon_partner_tz-14.0.1.0.1.dist-info/top_level.txt
odoo14_addon_partner_tz-14.0.1.0.1.dist-info/RECORD
